ninthCounter.v
module ninthCounter(q, clk, reset);
    input clk, reset;
    output [8:0]q;
    wire [8:0]p;

    D_FF dff1(p[0], p[8], clk, reset , 1'b0);
    D_FF dff2(p[1], p[0], clk, 1'b0 , reset);
    D_FF dff3(p[2], p[1], clk, 1'b0 , reset);
    D_FF dff4(p[3], p[2], clk, 1'b0 , reset);
    D_FF dff5(p[4], p[3], clk, 1'b0 , reset);
    D_FF dff6(p[5], p[4], clk, 1'b0 , reset);
    D_FF dff7(p[6], p[5], clk, 1'b0 , reset);
    D_FF dff8(p[7], p[6], clk, 1'b0 , reset);
    D_FF dff9(p[8], p[7], clk, 1'b0 , reset);

    and and1(q[0], p[0] ,clk);
    and and2(q[1], p[1] ,clk);
    and and3(q[2], p[2] ,clk);
    and and4(q[3], p[3] ,clk);
    and and5(q[4], p[4] ,clk);
    and and6(q[5], p[5] ,clk);
    and and7(q[6], p[6] ,clk);
    and and8(q[7], p[7] ,clk);
    and and9(q[8], p[8] ,clk);
endmodule

module D_FF (q, d, clk, preset, reset);
	input d, clk, preset, reset;
	output q;
	reg q;

	always @(posedge reset or posedge preset or posedge clk)
        if(reset)
            q <= 1'b0;
        else if(preset)
            q <= 1'b1;
        else
            q <= d;
endmodule

stims/ninthCounterSTIM.v
module ninthCounterSTIM;
    reg clk;
    reg reset;
    wire [8:0]q;
    ninthCounter nctr(q,clk,reset);

	initial
		begin
			$dumpfile("ninthCounter.vcd");
			$dumpvars(0,ninthCounterSTIM);
			clk = 1'b0;  // set clk to 0
			reset = 1'b0;  // set reset to 0
		end

    initial 
        clk = 1'b0;
    always
        #4 clk = ~clk;

    initial
        begin
            #1 reset = 1'b1;
            #3 reset = 1'b0;
            #40 reset = 1'b1;
            #42 reset = 1'b0;
            #100 $finish;
        end    

    initial
        $monitor($time, " output q = %d reset = %d, clk = %d", q[0], reset, clk);
    
endmodule

waves/ninthCounter.vcd
$date
	Sat Oct 08 10:57:02 2022
$end
$version
	Icarus Verilog
$end
$timescale
	1s
$end
$scope module ninthCounterSTIM $end
$var wire 9 ! q [8:0] $end
$var reg 1 " clk $end
$var reg 1 # reset $end
$scope module nctr $end
$var wire 1 " clk $end
$var wire 1 # reset $end
$var wire 9 $ q [8:0] $end
$var wire 9 % p [8:0] $end
$scope module dff1 $end
$var wire 1 " clk $end
$var wire 1 & d $end
$var wire 1 # preset $end
$var wire 1 ' reset $end
$var reg 1 ( q $end
$upscope $end
$scope module dff2 $end
$var wire 1 " clk $end
$var wire 1 ) d $end
$var wire 1 * preset $end
$var wire 1 # reset $end
$var reg 1 + q $end
$upscope $end
$scope module dff3 $end
$var wire 1 " clk $end
$var wire 1 , d $end
$var wire 1 - preset $end
$var wire 1 # reset $end
$var reg 1 . q $end
$upscope $end
$scope module dff4 $end
$var wire 1 " clk $end
$var wire 1 / d $end
$var wire 1 0 preset $end
$var wire 1 # reset $end
$var reg 1 1 q $end
$upscope $end
$scope module dff5 $end
$var wire 1 " clk $end
$var wire 1 2 d $end
$var wire 1 3 preset $end
$var wire 1 # reset $end
$var reg 1 4 q $end
$upscope $end
$scope module dff6 $end
$var wire 1 " clk $end
$var wire 1 5 d $end
$var wire 1 6 preset $end
$var wire 1 # reset $end
$var reg 1 7 q $end
$upscope $end
$scope module dff7 $end
$var wire 1 " clk $end
$var wire 1 8 d $end
$var wire 1 9 preset $end
$var wire 1 # reset $end
$var reg 1 : q $end
$upscope $end
$scope module dff8 $end
$var wire 1 " clk $end
$var wire 1 ; d $end
$var wire 1 < preset $end
$var wire 1 # reset $end
$var reg 1 = q $end
$upscope $end
$scope module dff9 $end
$var wire 1 " clk $end
$var wire 1 > d $end
$var wire 1 ? preset $end
$var wire 1 # reset $end
$var reg 1 @ q $end
$upscope $end
$upscope $end
$upscope $end
$enddefinitions $end
$comment Show the parameter values. $end
$dumpall
$end
#0
$dumpvars
x@
0?
x>
x=
0<
x;
x:
09
x8
x7
06
x5
x4
03
x2
x1
00
x/
x.
0-
x,
x+
0*
x)
x(
0'
x&
bx %
b0 $
0#
0"
b0 !
$end
#1
1)
0,
0/
02
05
08
0;
0>
0&
1(
0+
0.
01
04
07
0:
0=
b1 %
0@
1#
#4
0)
1,
0(
b10 %
1+
b10 !
b10 $
0#
1"
#8
b0 !
b0 $
0"
#12
0,
1/
0+
b100 %
1.
b100 !
b100 $
1"
#16
b0 !
b0 $
0"
#20
0/
12
0.
b1000 %
11
b1000 !
b1000 $
1"
#24
b0 !
b0 $
0"
#28
02
15
01
b10000 %
14
b10000 !
b10000 $
1"
#32
b0 !
b0 $
0"
#36
05
18
04
b100000 %
17
b100000 !
b100000 $
1"
#40
b0 !
b0 $
0"
#44
1)
08
1(
b1 %
07
b1 !
b1 $
1"
1#
#48
b0 !
b0 $
0"
#52
b1 !
b1 $
1"
#56
b0 !
b0 $
0"
#60
b1 !
b1 $
1"
#64
b0 !
b0 $
0"
#68
b1 !
b1 $
1"
#72
b0 !
b0 $
0"
#76
b1 !
b1 $
1"
#80
b0 !
b0 $
0"
#84
b1 !
b1 $
1"
#86
0#
#88
b0 !
b0 $
0"
#92
0)
1,
0(
b10 %
1+
b10 !
b10 $
1"
#96
b0 !
b0 $
0"
#100
0,
1/
0+
b100 %
1.
b100 !
b100 $
1"
#104
b0 !
b0 $
0"
#108
0/
12
0.
b1000 %
11
b1000 !
b1000 $
1"
#112
b0 !
b0 $
0"
#116
02
15
01
b10000 %
14
b10000 !
b10000 $
1"
#120
b0 !
b0 $
0"
#124
05
18
04
b100000 %
17
b100000 !
b100000 $
1"
#128
b0 !
b0 $
0"
#132
08
1;
07
b1000000 %
1:
b1000000 !
b1000000 $
1"
#136
b0 !
b0 $
0"
#140
0;
1>
0:
b10000000 %
1=
b10000000 !
b10000000 $
1"
#144
b0 !
b0 $
0"
#148
0>
1&
0=
b100000000 %
1@
b100000000 !
b100000000 $
1"
#152
b0 !
b0 $
0"
#156
1)
0&
1(
b1 %
0@
b1 !
b1 $
1"
#160
b0 !
b0 $
0"
#164
0)
1,
0(
b10 %
1+
b10 !
b10 $
1"
#168
b0 !
b0 $
0"
#172
0,
1/
0+
b100 %
1.
b100 !
b100 $
1"
#176
b0 !
b0 $
0"
#180
0/
12
0.
b1000 %
11
b1000 !
b1000 $
1"
#184
b0 !
b0 $
0"
